VsCodeQuestasim-main/src/FIFO_no_sintetizable.sv
module FIFO_no_sintetizable
#(parameter DEPTH=32, parameter WIDTH=8)
 
  ( input   logic CLOCK,//!reloj de sistema
  input  logic RESET_N, //!reset asíncrono activo en bajo
   input  logic CLEAR_N, //!limpia la fifo, activo en bajo
   input  logic [WIDTH-1:0] DATA_IN, //!dato a escribir en la fifo
   input  logic READ, //!señal de lectura
   input  logic WRITE, //!señal de escritura
   output logic [WIDTH-1:0] DATA_OUT, //!dato leido de la fifo
   output logic [$clog2(DEPTH):0] USE_DW, //!número de palabras usadas en la fifo
   output logic F_EMPTY_N, //!fifo vacía activo a nivel bajo
   output logic F_FULL_N //!fifo llena activo a nivel bajo
  );
   
   
 
   
  logic [WIDTH-1:0] cola [$:DEPTH] ;//cola idealmente de tamaño DEPTH
 
 
   
always_ff @(negedge RESET_N, posedge CLOCK)
if (!RESET_N)
begin
  cola.delete(); 
  DATA_OUT<='0;
end
else
if (!CLEAR_N)
begin
  cola.delete();
  DATA_OUT<='0;
end
else
  begin
    case ({READ,WRITE})
      2'b01: if (cola.size<DEPTH) cola.push_front(DATA_IN);
      2'b10: DATA_OUT<=cola.pop_back(); 
      2'b11: begin
 
              cola.push_front(DATA_IN);              
              DATA_OUT<=cola.pop_back(); 
            end
 
    endcase
 
  end
 
  assign  USE_DW=cola.size();
  assign  F_FULL_N=!(cola.size()==DEPTH);
  assign  F_EMPTY_N=!(cola.size()==0); 
      
 
  
property  llenado ;
    (@(posedge CLOCK) not (WRITE==1'b1 && F_FULL_N==1'b0 &&READ==1'b0));
endproperty
sobrellenado:assert property (llenado)  else $error("estas escribiendo sobre una fifo llena");
 
property  vaciado ;
  (@(posedge CLOCK) not (READ==1'b1 && F_EMPTY_N==1'b0&& WRITE==1'b0)) ;
endproperty
sobrevaciado:assert property  (vaciado) else $error("estas leyendo de una fifo vacia");
   
 
endmodule

src/FIFO_tb_v0.sv
//Code 
`timescale 1 ns/ 1 ps

module FIFO_tb_v0();
 
parameter DEPTH=32, WIDTH=8;
localparam ADDRESS=$clog2(DEPTH);
  
logic  clock, reset, rden,wren,clear;
logic  [WIDTH-1:0] data_in;
logic  [ADDRESS:0] use_dw;
 
 
 
logic [4:0] rdaddress;
 
logic [4:0] wraddress;
 
logic full,empty;                                              
logic [WIDTH-1:0]  data_out;
 
 
 
//Modelo de la FIFO
 
logic [7:0] FIFO_ideal [$]; //Definida con una cola
mailbox FIFO_ideal_mbox = new(); //definida con un mailbox
 
// Instancia del DUV
FIFO_no_sintetizable DUV (.CLOCK(clock),
               .RESET_N(reset),
               .DATA_IN(data_in),
               .READ(rden),
               .WRITE(wren),
               .CLEAR_N(1'b1),
               .F_FULL_N(full),
               .F_EMPTY_N(empty),
               .USE_DW(use_dw),
               .DATA_OUT(data_out));
 
 
 
 
 
// Casos de Test      
initial
begin
$info("INICIO VALIDACION");
inicializacion();
 
$info("*** TEST 1: Escritura simple");
test_A();
$info("*** FIN TEST 1 ****");
 
 
 
$info   ("*** TEST 2: LLenado simple de la FIFO");
resetON();
llenar_simple();
$info("*** FIN TEST 2 ****");
 
 
$info("*** TEST 3: Escritura y lectura simultanea con FIFO vacia");
resetON();
lectura_escritura(10,10);
$info("*** FIN TEST 3 ****");
 
$info("*** TEST 3: Escritura y lectura simultanea con FIFO llena");
resetON();
test_B();
$info("*** FIN TEST 3 ****");
 
$info("*** TEST 4: Llenado y vaciado de la FIFO");
resetON();
test_C();
$info("*** FIN TEST 4 ****");
 
$info("*** TEST 5: Escritura y lectura aleatoria con FIFO vacia, llena y a mitad.");
resetON();
test_D();
$info("*** FIN TEST 5 ****");
 
 
repeat(5) @(posedge clock);
$info("FIN VALIDACION");
$stop;
end
 
 
initial begin
  $dumpfile("FIFO_TB.vcd");
  $dumpvars(0,FIFO_tb_v0.DUV);
end 
         
 
assign clear = 1'b1;
// Generación de reloj
initial                                               
begin  
 clock = 1'b0;                                               
 forever #10 clock = !clock;                    
end
 
 
 
 
// Inicialización de las entradas   
task init_inputs();
begin
  data_in <='0;
  wren <= 1'b0;
  rden <= 1'b0;
end
endtask
// Generación de reset
task resetON();
begin
#10 reset=1'b0;
FIFO_ideal={};
repeat(5) @(posedge clock);
#7 reset=1'b1;
end
endtask
 
// Escritura de datos en la FIFO. 
// La entrada define el número de datos a escribir   
task solo_escritura(input integer n_escrituras);
begin
logic [7:0] dato;
wren<=1'b0;
@(negedge clock) 
wren<=1'b1;
repeat (n_escrituras) begin
 dato = $random%256;
 data_in = dato;
 FIFO_ideal.push_front(dato);
 @(negedge clock);
end
wren <= 1'b0;
end
endtask
// Lectura de datos de la FIFO, el número de datos a leer
// Monitoriza la salida.
task solo_lectura(input integer n_lecturas);
logic [7:0] dato;
begin
  rden <= 1'b0;
  @(negedge clock);
  rden <= 1'b1;
  repeat (n_lecturas) begin
    @(negedge clock);
    dato = FIFO_ideal.pop_back();
    assert (dato == data_out) else $error("ERROR el dato leido %h no coincide con el esperado %h", dato, data_out);
  end
  rden <= 1'b0;
end
endtask
// Lectura y escritura de datos simultanea. Se definen cuantos datos a leer y a escribir.
task lectura_escritura( input integer n_lecturas, input integer n_escrituras);
fork
solo_escritura(n_escrituras);
solo_lectura(n_lecturas);
join
endtask
 
 
 
    //Monitor de palabras en la fifo
    // palabras en la fifo
integer palabras;
always @(posedge clock, negedge reset)
if (!reset) palabras=0;
    else if (!clear) palabras=0;
else
   case({wren,rden})
   2'b01: palabras = palabras-1;
   2'b10: palabras = palabras+1;
   endcase
// Asserciones de control de la FIFO
 
   always @(negedge clock)
begin
if (reset && clear) begin
   assert ((!empty)?(palabras == 0):(palabras != 0)) else $error("ERROR señal de FIFO vacía activada incorrectamente");
   assert ((!full)? (palabras == 32):(palabras != 32)) else $error("ERROR señal de FIFO llena activada incorrectamente");
   assert (palabras <= 32) else $error("ERROR FIFO con tamaño  incorrecto");
   assert (palabras[5:0] == use_dw) else $error("ERROR USE_DW no funciona como se espera");
end
end
 
 
//empiezan los tasks de alto nivel:casos de test
 
 
task inicializacion;
begin
$display("Inicializacion de las entradas");
init_inputs();
$display(" reset inicial");
resetON();
end
endtask
 
// Escritura simple de dos valores y una lectura.
task test_A;
begin
$display(" escribo dos valores");
solo_escritura(1);
solo_escritura(1);
$display("leo un valor");
solo_lectura(1);
end
endtask
 
// Escritura y lectura simultanea con fifo llena.
task test_B;
begin
llenar_simple();
lectura_escritura(10,10);
end
endtask
 
// Test de llenado y vaciado.
task test_C;
begin
 
llenar_simple;
vaciado_simple();
lectura_escritura(10,10);
end
endtask
 
 
 
task test_D;
begin
  vaciado_simple();
  rd_wr_random(100);
  llenar_simple();
  rd_wr_random(100);
  vaciado_simple();
  solo_escritura(15);
  rd_wr_random(100);
end
endtask
 
 // Escrituras y lecturas aleatorias.
 task rd_wr_random(integer numero);
 begin
   integer caso;   
   repeat(numero) begin
   caso = $random%3;
   case (caso)
    0: if (empty) solo_lectura(1);
    1: if (full) solo_escritura(1);
    2:  lectura_escritura(1,1);
    endcase
   end
 end
  
endtask
 
// Task de llenado de la FIFO
task llenar_simple();
logic [7:0]cuenta;
begin
 cuenta<=8'b0;
 while (full==1'b1)
 begin
  solo_escritura(1);
  cuenta++;
 end
   
end
endtask
 
// Task de vaciado de la FIFO
task vaciado_simple();
logic [7:0]cuenta;
begin
 cuenta<=8'b0;
 while (empty==1'b1)
 begin
  solo_lectura(1);
  cuenta++;
 end
  
  
end
endtask
endmodule
// or browse Examples

VsCodeQuestasim-main/sim/FIFO_TB.vcd
$date
	Tue Sep 15 16:50:15 2026
$end
$version
	QuestaSim Version 2025.1_2
$end
$timescale
	1ps
$end

$scope module FIFO_tb_v0 $end

$scope module DUV $end
$var parameter 32 ! DEPTH $end
$var parameter 32 " WIDTH $end
$var wire 1 # CLOCK $end
$var wire 1 $ RESET_N $end
$var wire 1 % CLEAR_N $end
$var wire 1 & DATA_IN [7] $end
$var wire 1 ' DATA_IN [6] $end
$var wire 1 ( DATA_IN [5] $end
$var wire 1 ) DATA_IN [4] $end
$var wire 1 * DATA_IN [3] $end
$var wire 1 + DATA_IN [2] $end
$var wire 1 , DATA_IN [1] $end
$var wire 1 - DATA_IN [0] $end
$var wire 1 . READ $end
$var wire 1 / WRITE $end
$var reg 8 0 DATA_OUT [7:0] $end
$var reg 6 1 USE_DW [5:0] $end
$var reg 1 2 F_EMPTY_N $end
$var reg 1 3 F_FULL_N $end

$scope begin sobrellenado $end
$upscope $end

$scope begin sobrevaciado $end
$upscope $end
$upscope $end
$upscope $end
$enddefinitions $end
#0
$dumpvars
bx 0
b0 1
02
13
b100000 !
b1000 "
0/
0.
0-
0,
0+
0*
0)
0(
0'
0&
1%
x$
0#
$end
#10000
0$
1#
b0 0
#20000
0#
#30000
1#
#40000
0#
#50000
1#
#60000
0#
#70000
1#
#80000
0#
#90000
1#
#97000
1$
#100000
0#
1+
1(
1/
#110000
1#
b1 1
12
#120000
0#
0/
#130000
1#
#140000
0#
1-
0+
0(
1&
1/
#150000
1#
b10 1
#160000
0#
0/
#170000
1#
#180000
0#
1.
#190000
1#
b1 1
b100100 0
#200000
0#
0.
#210000
1#
0$
b0 1
02
b0 0
#220000
0#
#230000
1#
#240000
0#
#250000
1#
#260000
0#
#270000
1#
#280000
0#
#290000
1#
#300000
0#
#310000
1#
#317000
1$
#320000
0#
1*
0&
1/
#330000
1#
b1 1
12
#340000
0#
0/
#350000
1#
#360000
0#
1,
0*
1(
1'
1/
#370000
1#
b10 1
#380000
0#
0/
#390000
1#
#400000
0#
0,
1+
1*
0(
0'
1/
#410000
1#
b11 1
#420000
0#
0/
#430000
1#
#440000
0#
1&
1/
#450000
1#
b100 1
#460000
0#
0/
#470000
1#
#480000
0#
0*
1(
1'
0&
1/
#490000
1#
b101 1
#500000
0#
0/
#510000
1#
#520000
0#
0-
1,
0+
1)
0(
0'
1/
#530000
1#
b110 1
#540000
0#
0/
#550000
1#
#560000
0#
1-
0,
0)
1/
#570000
1#
b111 1
#580000
0#
0/
#590000
1#
#600000
0#
1+
1*
1/
#610000
1#
b1000 1
#620000
0#
0/
#630000
1#
#640000
0#
0-
1,
0*
1)
1(
1'
1/
#650000
1#
b1001 1
#660000
0#
0/
#670000
1#
#680000
0#
1-
0,
1*
0'
1/
#690000
1#
b1010 1
#700000
0#
0/
#710000
1#
#720000
0#
0)
1'
1&
1/
#730000
1#
b1011 1
#740000
0#
0/
#750000
1#
#760000
0#
0-
0(
0'
1/
#770000
1#
b1100 1
#780000
0#
0/
#790000
1#
#800000
0#
1-
0+
1)
1(
1'
1/
#810000
1#
b1101 1
#820000
0#
0/
#830000
1#
#840000
0#
0-
1,
1+
0*
0)
0(
1/
#850000
1#
b1110 1
#860000
0#
0/
#870000
1#
#880000
0#
1-
0,
1/
#890000
1#
b1111 1
#900000
0#
0/
#910000
1#
#920000
0#
0-
1,
0+
1*
1(
0'
1/
#930000
1#
b10000 1
#940000
0#
0/
#950000
1#
#960000
0#
1-
0,
1+
0*
1'
1/
#970000
1#
b10001 1
#980000
0#
0/
#990000
1#
#1000000
0#
1,
1)
0&
1/
#1010000
1#
b10010 1
#1020000
0#
0/
#1030000
1#
#1040000
0#
0-
0+
0(
0'
1/
#1050000
1#
b10011 1
#1060000
0#
0/
#1070000
1#
#1080000
0#
1-
1+
1*
0)
1&
1/
#1090000
1#
b10100 1
#1100000
0#
0/
#1110000
1#
#1120000
0#
0-
0+
0*
1)
1(
1'
1/
#1130000
1#
b10101 1
#1140000
0#
0/
#1150000
1#
#1160000
0#
1+
1*
0)
0(
1/
#1170000
1#
b10110 1
#1180000
0#
0/
#1190000
1#
#1200000
0#
0,
0+
1(
1/
#1210000
1#
b10111 1
#1220000
0#
0/
#1230000
1#
#1240000
0#
1-
1+
0*
0(
1/
#1250000
1#
b11000 1
#1260000
0#
0/
#1270000
1#
#1280000
0#
0-
1*
1)
0&
1/
#1290000
1#
b11001 1
#1300000
0#
0/
#1310000
1#
#1320000
0#
1-
1(
0'
1&
1/
#1330000
1#
b11010 1
#1340000
0#
0/
#1350000
1#
#1360000
0#
0)
0&
1/
#1370000
1#
b11011 1
#1380000
0#
0/
#1390000
1#
#1400000
0#
0*
1'
1/
#1410000
1#
b11100 1
#1420000
0#
0/
#1430000
1#
#1440000
0#
1,
0+
1/
#1450000
1#
b11101 1
#1460000
0#
0/
#1470000
1#
#1480000
0#
0-
1*
0(
0'
1/
#1490000
1#
b11110 1
#1500000
0#
0/
#1510000
1#
#1520000
0#
0,
0*
1&
1/
#1530000
1#
b11111 1
#1540000
0#
0/
#1550000
1#
#1560000
0#
1(
0&
1/
#1570000
1#
b100000 1
03
#1580000
0#
0/
#1590000
1#
0$
b0 1
13
02
#1600000
0#
#1610000
1#
#1620000
0#
#1630000
1#
#1640000
0#
#1650000
1#
#1660000
0#
#1670000
1#
#1680000
0#
#1690000
1#
#1697000
1$
#1700000
0#
1,
1*
1&
1.
1/
#1710000
1#
b10101010 0
#1720000
0#
1-
0,
1+
1)
0(
#1730000
1#
b10011101 0
#1740000
0#
0-
1,
0*
#1750000
1#
b10010110 0
#1760000
0#
1-
0+
0&
#1770000
1#
b10011 0
#1780000
0#
0,
1+
1*
0)
#1790000
1#
b1101 0
#1800000
0#
1,
0+
0*
1)
1'
#1810000
1#
b1010011 0
#1820000
0#
1*
0)
1(
#1830000
1#
b1101011 0
#1840000
0#
0,
1+
0*
1)
0(
1&
#1850000
1#
b11010101 0
#1860000
0#
0-
1,
0+
0)
0'
0&
#1870000
1#
b10 0
#1880000
0#
1+
1*
1(
1&
#1890000
1#
b10101110 0
#1900000
0#
0.
0/
#1910000
1#
0$
b0 0
#1920000
0#
#1930000
1#
#1940000
0#
#1950000
1#
#1960000
0#
#1970000
1#
#1980000
0#
#1990000
1#
#2000000
0#
#2010000
1#
#2017000
1$
#2020000
0#
1-
0,
1)
0(
0&
1/
#2030000
1#
b1 1
12
#2040000
0#
0/
#2050000
1#
#2060000
0#
1,
0)
1'
1&
1/
#2070000
1#
b10 1
#2080000
0#
0/
#2090000
1#
#2100000
0#
0+
0*
1(
0'
0&
1/
#2110000
1#
b11 1
#2120000
0#
0/
#2130000
1#
#2140000
0#
0-
1*
0(
1/
#2150000
1#
b100 1
#2160000
0#
0/
#2170000
1#
#2180000
0#
1'
1&
1/
#2190000
1#
b101 1
#2200000
0#
0/
#2210000
1#
#2220000
0#
0,
1+
1)
1(
0'
0&
1/
#2230000
1#
b110 1
#2240000
0#
0/
#2250000
1#
#2260000
0#
1,
0+
0*
1'
1&
1/
#2270000
1#
b111 1
#2280000
0#
0/
#2290000
1#
#2300000
0#
1*
0)
0(
0'
1/
#2310000
1#
b1000 1
#2320000
0#
0/
#2330000
1#
#2340000
0#
1-
0,
0*
1'
0&
1/
#2350000
1#
b1001 1
#2360000
0#
0/
#2370000
1#
#2380000
0#
0-
1*
1)
1&
1/
#2390000
1#
b1010 1
#2400000
0#
0/
#2410000
1#
#2420000
0#
1(
0&
1/
#2430000
1#
b1011 1
#2440000
0#
0/
#2450000
1#
#2460000
0#
1-
0)
0(
0'
1&
1/
#2470000
1#
b1100 1
#2480000
0#
0/
#2490000
1#
#2500000
0#
1,
1(
1'
1/
#2510000
1#
b1101 1
#2520000
0#
0/
#2530000
1#
#2540000
0#
0-
1+
0*
1)
0'
1/
#2550000
1#
b1110 1
#2560000
0#
0/
#2570000
1#
#2580000
0#
0)
0(
1'
1/
#2590000
1#
b1111 1
#2600000
0#
0/
#2610000
1#
#2620000
0#
1*
1(
0'
1/
#2630000
1#
b10000 1
#2640000
0#
0/
#2650000
1#
#2660000
0#
0,
1)
1/
#2670000
1#
b10001 1
#2680000
0#
0/
#2690000
1#
#2700000
0#
1,
0+
0)
0&
1/
#2710000
1#
b10010 1
#2720000
0#
0/
#2730000
1#
#2740000
0#
1-
0(
1/
#2750000
1#
b10011 1
#2760000
0#
0/
#2770000
1#
#2780000
0#
0,
0*
1)
1(
1'
1/
#2790000
1#
b10100 1
#2800000
0#
0/
#2810000
1#
#2820000
0#
1+
0)
0(
0'
1&
1/
#2830000
1#
b10101 1
#2840000
0#
0/
#2850000
1#
#2860000
0#
1,
1*
1'
0&
1/
#2870000
1#
b10110 1
#2880000
0#
0/
#2890000
1#
#2900000
0#
0+
1)
1(
0'
1/
#2910000
1#
b10111 1
#2920000
0#
0/
#2930000
1#
#2940000
0#
0-
1/
#2950000
1#
b11000 1
#2960000
0#
0/
#2970000
1#
#2980000
0#
1+
1'
1/
#2990000
1#
b11001 1
#3000000
0#
0/
#3010000
1#
#3020000
0#
1-
0,
0*
0(
0'
1/
#3030000
1#
b11010 1
#3040000
0#
0/
#3050000
1#
#3060000
0#
0+
1(
1'
1&
1/
#3070000
1#
b11011 1
#3080000
0#
0/
#3090000
1#
#3100000
0#
1*
0(
1/
#3110000
1#
b11100 1
#3120000
0#
0/
#3130000
1#
#3140000
0#
0-
1,
0*
0)
1(
0&
1/
#3150000
1#
b11101 1
#3160000
0#
0/
#3170000
1#
#3180000
0#
0,
1+
1*
0(
1/
#3190000
1#
b11110 1
#3200000
0#
0/
#3210000
1#
#3220000
0#
1-
1,
1)
0'
1&
1/
#3230000
1#
b11111 1
#3240000
0#
0/
#3250000
1#
#3260000
0#
0)
1/
#3270000
1#
b100000 1
03
#3280000
0#
0/
#3290000
1#
#3300000
0#
0-
0,
0+
1)
1(
1'
1.
1/
#3310000
1#
b11101 0
#3320000
0#
1-
1,
1+
0*
0'
#3330000
1#
b11001111 0
#3340000
0#
1*
0(
#3350000
1#
b100011 0
#3360000
0#
0-
0,
1'
0&
#3370000
1#
b1010 0
#3380000
0#
1-
1,
0+
#3390000
1#
b11001010 0
#3400000
0#
0,
0)
0'
1&
#3410000
1#
b111100 0
#3420000
0#
1'
0&
#3430000
1#
b11110010 0
#3440000
0#
0-
0*
1)
1&
#3450000
1#
b10001010 0
#3460000
0#
1-
1,
1+
#3470000
1#
b1000001 0
#3480000
0#
0,
0+
0&
#3490000
1#
b11011000 0
#3500000
0#
0.
0/
#3510000
1#
0$
b0 1
13
02
b0 0
#3520000
0#
#3530000
1#
#3540000
0#
#3550000
1#
#3560000
0#
#3570000
1#
#3580000
0#
#3590000
1#
#3600000
0#
#3610000
1#
#3617000
1$
#3620000
0#
0-
1,
1+
0'
1&
1/
#3630000
1#
b1 1
12
#3640000
0#
0/
#3650000
1#
#3660000
0#
0,
1*
0)
0&
1/
#3670000
1#
b10 1
#3680000
0#
0/
#3690000
1#
#3700000
0#
1,
0+
0*
1'
1&
1/
#3710000
1#
b11 1
#3720000
0#
0/
#3730000
1#
#3740000
0#
0,
1*
1/
#3750000
1#
b100 1
#3760000
0#
0/
#3770000
1#
#3780000
0#
1-
1,
1+
0*
1)
1(
0&
1/
#3790000
1#
b101 1
#3800000
0#
0/
#3810000
1#
#3820000
0#
0,
1*
0'
1/
#3830000
1#
b110 1
#3840000
0#
0/
#3850000
1#
#3860000
0#
0-
1,
0+
0*
0(
1/
#3870000
1#
b111 1
#3880000
0#
0/
#3890000
1#
#3900000
0#
1+
1*
1(
1'
1/
#3910000
1#
b1000 1
#3920000
0#
0/
#3930000
1#
#3940000
0#
1-
0,
0)
1/
#3950000
1#
b1001 1
#3960000
0#
0/
#3970000
1#
#3980000
0#
0+
1)
0'
1/
#3990000
1#
b1010 1
#4000000
0#
0/
#4010000
1#
#4020000
0#
1,
1+
0(
1/
#4030000
1#
b1011 1
#4040000
0#
0/
#4050000
1#
#4060000
0#
0+
0*
1'
1&
1/
#4070000
1#
b1100 1
#4080000
0#
0/
#4090000
1#
#4100000
0#
0,
1+
0)
0'
1/
#4110000
1#
b1101 1
#4120000
0#
0/
#4130000
1#
#4140000
0#
0-
0+
1*
1)
1(
1'
0&
1/
#4150000
1#
b1110 1
#4160000
0#
0/
#4170000
1#
#4180000
0#
1-
1,
0(
1/
#4190000
1#
b1111 1
#4200000
0#
0/
#4210000
1#
#4220000
0#
0,
0)
1/
#4230000
1#
b10000 1
#4240000
0#
0/
#4250000
1#
#4260000
0#
1,
1+
1)
1(
0'
1/
#4270000
1#
b10001 1
#4280000
0#
0/
#4290000
1#
#4300000
0#
0-
0+
0)
1/
#4310000
1#
b10010 1
#4320000
0#
0/
#4330000
1#
#4340000
0#
0,
1)
0(
1'
1/
#4350000
1#
b10011 1
#4360000
0#
0/
#4370000
1#
#4380000
0#
1,
1+
0*
0)
0'
1&
1/
#4390000
1#
b10100 1
#4400000
0#
0/
#4410000
1#
#4420000
0#
1*
1/
#4430000
1#
b10101 1
#4440000
0#
0/
#4450000
1#
#4460000
0#
0,
1)
1/
#4470000
1#
b10110 1
#4480000
0#
0/
#4490000
1#
#4500000
0#
1,
0+
1(
1'
1/
#4510000
1#
b10111 1
#4520000
0#
0/
#4530000
1#
#4540000
0#
1+
0*
0)
0'
0&
1/
#4550000
1#
b11000 1
#4560000
0#
0/
#4570000
1#
#4580000
0#
1-
0+
1)
1'
1/
#4590000
1#
b11001 1
#4600000
0#
0/
#4610000
1#
#4620000
0#
0)
0'
1&
1/
#4630000
1#
b11010 1
#4640000
0#
0/
#4650000
1#
#4660000
0#
1+
1*
0&
1/
#4670000
1#
b11011 1
#4680000
0#
0/
#4690000
1#
#4700000
0#
0+
0*
1)
1&
1/
#4710000
1#
b11100 1
#4720000
0#
0/
#4730000
1#
#4740000
0#
1+
1*
0(
1'
0&
1/
#4750000
1#
b11101 1
#4760000
0#
0/
#4770000
1#
#4780000
0#
0-
0,
0*
0)
1/
#4790000
1#
b11110 1
#4800000
0#
0/
#4810000
1#
#4820000
0#
1-
1,
1)
1(
1&
1/
#4830000
1#
b11111 1
#4840000
0#
0/
#4850000
1#
#4860000
0#
0+
1*
0)
0(
1/
#4870000
1#
b100000 1
03
#4880000
0#
0/
#4890000
1#
#4900000
0#
1.
#4910000
1#
b11111 1
13
b10010110 0
#4920000
0#
0.
#4930000
1#
#4940000
0#
1.
#4950000
1#
b11110 1
b1100 0
#4960000
0#
0.
#4970000
1#
#4980000
0#
1.
#4990000
1#
b11101 1
b11000010 0
#5000000
0#
0.
#5010000
1#
#5020000
0#
1.
#5030000
1#
b11100 1
b11001000 0
#5040000
0#
0.
#5050000
1#
#5060000
0#
1.
#5070000
1#
b11011 1
b1110111 0
#5080000
0#
0.
#5090000
1#
#5100000
0#
1.
#5110000
1#
b11010 1
b111101 0
#5120000
0#
0.
#5130000
1#
#5140000
0#
1.
#5150000
1#
b11001 1
b10010 0
#5160000
0#
0.
#5170000
1#
#5180000
0#
1.
#5190000
1#
b11000 1
b1111110 0
#5200000
0#
0.
#5210000
1#
#5220000
0#
1.
#5230000
1#
b10111 1
b1101101 0
#5240000
0#
0.
#5250000
1#
#5260000
0#
1.
#5270000
1#
b10110 1
b111001 0
#5280000
0#
0.
#5290000
1#
#5300000
0#
1.
#5310000
1#
b10101 1
b11111 0
#5320000
0#
0.
#5330000
1#
#5340000
0#
1.
#5350000
1#
b10100 1
b11010011 0
#5360000
0#
0.
#5370000
1#
#5380000
0#
1.
#5390000
1#
b10011 1
b10000101 0
#5400000
0#
0.
#5410000
1#
#5420000
0#
1.
#5430000
1#
b10010 1
b1111000 0
#5440000
0#
0.
#5450000
1#
#5460000
0#
1.
#5470000
1#
b10001 1
b1011011 0
#5480000
0#
0.
#5490000
1#
#5500000
0#
1.
#5510000
1#
b10000 1
b1001001 0
#5520000
0#
0.
#5530000
1#
#5540000
0#
1.
#5550000
1#
b1111 1
b111111 0
#5560000
0#
0.
#5570000
1#
#5580000
0#
1.
#5590000
1#
b1110 1
b101010 0
#5600000
0#
0.
#5610000
1#
#5620000
0#
1.
#5630000
1#
b1101 1
b1011000 0
#5640000
0#
0.
#5650000
1#
#5660000
0#
1.
#5670000
1#
b1100 1
b10000110 0
#5680000
0#
0.
#5690000
1#
#5700000
0#
1.
#5710000
1#
b1011 1
b10001110 0
#5720000
0#
0.
#5730000
1#
#5740000
0#
1.
#5750000
1#
b1010 1
b10011100 0
#5760000
0#
0.
#5770000
1#
#5780000
0#
1.
#5790000
1#
b1001 1
b11111010 0
#5800000
0#
0.
#5810000
1#
#5820000
0#
1.
#5830000
1#
b1000 1
b100110 0
#5840000
0#
0.
#5850000
1#
#5860000
0#
1.
#5870000
1#
b111 1
b1110011 0
#5880000
0#
0.
#5890000
1#
#5900000
0#
1.
#5910000
1#
b110 1
b10100011 0
#5920000
0#
0.
#5930000
1#
#5940000
0#
1.
#5950000
1#
b101 1
b101111 0
#5960000
0#
0.
#5970000
1#
#5980000
0#
1.
#5990000
1#
b100 1
b10110011 0
#6000000
0#
0.
#6010000
1#
#6020000
0#
1.
#6030000
1#
b11 1
b1011111 0
#6040000
0#
0.
#6050000
1#
#6060000
0#
1.
#6070000
1#
b10 1
b1000100 0
#6080000
0#
0.
#6090000
1#
#6100000
0#
1.
#6110000
1#
b1 1
b11110111 0
#6120000
0#
0.
#6130000
1#
#6140000
0#
1.
#6150000
1#
b0 1
02
b11001011 0
#6160000
0#
0.
#6170000
1#
#6180000
0#
0-
1+
0*
1(
1.
1/
#6190000
1#
b11100110 0
#6200000
0#
0+
1*
1)
0(
0&
#6210000
1#
b1011010 0
#6220000
0#
1-
0,
0)
1(
0'
#6230000
1#
b101001 0
#6240000
0#
1+
1'
1&
#6250000
1#
b11101101 0
#6260000
0#
0-
1,
0+
1)
0(
#6270000
1#
b11011010 0
#6280000
0#
1-
0,
1+
0*
0)
1(
0&
#6290000
1#
b1100101 0
#6300000
0#
1)
0'
1&
#6310000
1#
b10110101 0
#6320000
0#
1,
1*
0(
1'
#6330000
1#
b11011111 0
#6340000
0#
0,
0+
1(
0&
#6350000
1#
b1111001 0
#6360000
0#
0-
1+
0*
0)
0(
#6370000
1#
b1000100 0
#6380000
0#
0.
0/
#6390000
1#
0$
b0 0
#6400000
0#
#6410000
1#
#6420000
0#
#6430000
1#
#6440000
0#
#6450000
1#
#6460000
0#
#6470000
1#
#6480000
0#
#6490000
1#
#6497000
1$
#6500000
0#
1-
1,
0+
1*
1(
0'
1&
1.
1/
#6510000
1#
b10101011 0
#6520000
0#
0/
0.
#6530000
1#
#6540000
0#
0-
1)
0(
1.
1/
#6550000
1#
b10011010 0
#6560000
0#
0/
0.
#6570000
1#
#6580000
0#
1+
0)
1'
0&
1.
1/
#6590000
1#
b1001110 0
#6600000
0#
0/
0.
#6610000
1#
#6620000
0#
0,
0+
1)
1(
0'
1.
1/
#6630000
1#
b111000 0
#6640000
0#
0/
0.
#6650000
1#
#6660000
0#
1-
1,
0*
0(
1&
1/
#6670000
1#
b1 1
12
#6680000
0#
0/
#6690000
1#
#6700000
0#
1.
#6710000
1#
b0 1
02
b10010011 0
#6720000
0#
0.
#6730000
1#
#6740000
0#
0,
1+
1.
1/
#6750000
1#
b10010101 0
#6760000
0#
0/
0.
#6770000
1#
#6780000
0#
1,
1(
1'
1/
#6790000
1#
b1 1
12
#6800000
0#
0/
#6810000
1#
#6820000
0#
0-
0,
0'
1/
#6830000
1#
b10 1
#6840000
0#
0/
#6850000
1#
#6860000
0#
0+
1*
0)
0&
1/
#6870000
1#
b11 1
#6880000
0#
0/
#6890000
1#
#6900000
0#
1.
#6910000
1#
b10 1
b11110111 0
#6920000
0#
0.
#6930000
1#
#6940000
0#
1.
#6950000
1#
b1 1
b10110100 0
#6960000
0#
0.
#6970000
1#
#6980000
0#
1.
#6990000
1#
b0 1
02
b101000 0
#7000000
0#
0.
#7010000
1#
#7020000
0#
1-
1+
1)
1'
1&
1.
1/
#7030000
1#
b11111101 0
#7040000
0#
0/
0.
#7050000
1#
#7060000
0#
0-
0(
0'
0&
1/
#7070000
1#
b1 1
12
#7080000
0#
0/
#7090000
1#
#7100000
0#
1.
#7110000
1#
b0 1
02
b11100 0
#7120000
0#
0.
#7130000
1#
#7140000
0#
0+
0*
1(
1'
1.
1/
#7150000
1#
b1110000 0
#7160000
0#
0/
0.
#7170000
1#
#7180000
0#
1,
1+
1*
0(
1.
1/
#7190000
1#
b1011110 0
#7200000
0#
0/
0.
#7210000
1#
#7220000
0#
0+
0'
1/
#7230000
1#
b1 1
12
#7240000
0#
0/
#7250000
1#
#7260000
0#
1+
0*
1&
1.
1/
#7270000
1#
b11010 0
#7280000
0#
0/
0.
#7290000
1#
#7300000
0#
1.
#7310000
1#
b0 1
02
b10010110 0
#7320000
0#
0.
#7330000
1#
#7340000
0#
1(
1/
#7350000
1#
b1 1
12
#7360000
0#
0/
#7370000
1#
#7380000
0#
1.
#7390000
1#
b0 1
02
b10110110 0
#7400000
0#
0.
#7410000
1#
#7420000
0#
0)
0(
1.
1/
#7430000
1#
b10000110 0
#7440000
0#
0/
0.
#7450000
1#
#7460000
0#
1-
0+
1*
1)
1'
1.
1/
#7470000
1#
b11011011 0
#7480000
0#
0/
0.
#7490000
1#
#7500000
0#
0-
1(
1.
1/
#7510000
1#
b11111010 0
#7520000
0#
0/
0.
#7530000
1#
#7540000
0#
1-
0,
0*
0)
0'
1.
1/
#7550000
1#
b10100001 0
#7560000
0#
0/
0.
#7570000
1#
#7580000
0#
1+
1)
0&
1.
1/
#7590000
1#
b110101 0
#7600000
0#
0/
0.
#7610000
1#
#7620000
0#
0)
0(
1'
1&
1/
#7630000
1#
b1 1
12
#7640000
0#
0/
#7650000
1#
#7660000
0#
1,
0+
1)
1(
0&
1.
1/
#7670000
1#
b11000101 0
#7680000
0#
0/
0.
#7690000
1#
#7700000
0#
1.
#7710000
1#
b0 1
02
b1110011 0
#7720000
0#
0.
#7730000
1#
#7740000
0#
0,
0)
0'
1&
1/
#7750000
1#
b1 1
12
#7760000
0#
0/
#7770000
1#
#7780000
0#
0-
1,
1+
1'
1/
#7790000
1#
b10 1
#7800000
0#
0/
#7810000
1#
